DepthTensor/__init__.py
DepthTensor/autodiff.py
DepthTensor/tensor.py
DepthTensor/typing.py
DepthTensor/_core/__init__.py
DepthTensor/_core/exceptions.py
DepthTensor/_core/utils.py
DepthTensor/_core/ops/__init__.py
DepthTensor/_core/ops/comparison.py
DepthTensor/_core/ops/creation.py
DepthTensor/_core/ops/elementwise.py
DepthTensor/_core/ops/function.py
DepthTensor/_core/ops/reduction.py
DepthTensor/_core/random/__init__.py
DepthTensor/_core/random/generator.py
depthtensor-2.6.0.dist-info/licenses/LICENSE
depthtensor-2.6.0.dist-info/METADATA
depthtensor-2.6.0.dist-info/WHEEL
depthtensor-2.6.0.dist-info/top_level.txt
depthtensor-2.6.0.dist-info/RECORD
