Metadata-Version: 2.4
Name: depthtensor
Version: 2.6.0
Summary: A Hardware-Accelerated Tensor Computation and Autograd Engine
Author-email: Le Hong Ha <lehahong1310@gmail.com>
License: MIT License
Project-URL: Homepage, https://github.com/l-h-ha/DepthTensor
Project-URL: Bug Tracker, https://github.com/l-h-ha/DepthTensor/issues
Classifier: Programming Language :: Python :: 3
Classifier: Topic :: Scientific/Engineering :: Artificial Intelligence
Classifier: License :: OSI Approved :: MIT License
Classifier: Operating System :: OS Independent
Requires-Python: >=3.8
License-File: LICENSE
Requires-Dist: numpy
Provides-Extra: gpu
Requires-Dist: cupy; extra == "gpu"
Dynamic: license-file
